{
    "0100": "PIDs supported",
    "0101": "Monitor status since DTCs cleared. (Includes malfunction indicator lamp (MIL), status and number of DTCs, components tests, DTC readiness checks)",
    "0102": "DTC that caused freeze frame to be stored.",
    "0103": "Fuel system status",
    "0104": "Calculated engine load",
    "0105": "Engine coolant temperature",
    "0106": "Short term fuel trim (STFT)—Bank 1",
    "0107": "Long term fuel trim (LTFT)—Bank 1",
    "0108": "Short term fuel trim (STFT)—Bank 2",
    "0109": "Long term fuel trim (LTFT)—Bank 2",
    "010a": "Fuel pressure (gauge pressure)",
    "010b": "Intake manifold absolute pressure",
    "010c": "Engine speed",
    "010d": "Vehicle speed",
    "010e": "Timing advance",
    "010f": "Intake air temperature",
    "0110": "Mass air flow sensor (MAF) air flow rate",
    "0111": "Throttle position",
    "0112": "Commanded secondary air status",
    "0113": "Oxygen sensors present (in 2 banks)",
    "0114": "Oxygen Sensor 1 A: Voltage B: Short term fuel trim",
    "0115": "Oxygen Sensor 2 A: Voltage B: Short term fuel trim",
    "0116": "Oxygen Sensor 3 A: Voltage B: Short term fuel trim",
    "0117": "Oxygen Sensor 4 A: Voltage B: Short term fuel trim",
    "0118": "Oxygen Sensor 5 A: Voltage B: Short term fuel trim",
    "0119": "Oxygen Sensor 6 A: Voltage B: Short term fuel trim",
    "011a": "Oxygen Sensor 7 A: Voltage B: Short term fuel trim",
    "011b": "Oxygen Sensor 8 A: Voltage B: Short term fuel trim",
    "011c": "OBD standards this vehicle conforms to",
    "011d": "Oxygen sensors present (in 4 banks)",
    "011e": "Auxiliary input status",
    "011f": "Run time since engine start",
    "0120": "PIDs supported [$21 - $40]",
    "0121": "Distance traveled with malfunction indicator lamp (MIL) on",
    "0122": "Fuel Rail Pressure (relative to manifold vacuum)",
    "0123": "Fuel Rail Gauge Pressure (diesel, or gasoline direct injection)",
    "0124": "Oxygen Sensor 1 AB: Air-Fuel Equivalence Ratio (lambda,λ) CD: Voltage",
    "0125": "Oxygen Sensor 2 AB: Air-Fuel Equivalence Ratio (lambda,λ) CD: Voltage",
    "0126": "Oxygen Sensor 3 AB: Air-Fuel Equivalence Ratio (lambda,λ) CD: Voltage",
    "0127": "Oxygen Sensor 4 AB: Air-Fuel Equivalence Ratio (lambda,λ) CD: Voltage",
    "0128": "Oxygen Sensor 5 AB: Air-Fuel Equivalence Ratio (lambda,λ) CD: Voltage",
    "0129": "Oxygen Sensor 6 AB: Air-Fuel Equivalence Ratio (lambda,λ) CD: Voltage",
    "012a": "Oxygen Sensor 7 AB: Air-Fuel Equivalence Ratio (lambda,λ) CD: Voltage",
    "012b": "Oxygen Sensor 8 AB: Air-Fuel Equivalence Ratio (lambda,λ) CD: Voltage",
    "012c": "Commanded EGR",
    "012d": "EGR Error",
    "012e": "Commanded evaporative purge",
    "012f": "Fuel Tank Level Input",
    "0130": "Warm-ups since codes cleared",
    "0131": "Distance traveled since codes cleared",
    "0132": "Evap. System Vapor Pressure",
    "0133": "Absolute Barometric Pressure",
    "0134": "Oxygen Sensor 1 AB: Air-Fuel Equivalence Ratio (lambda,λ) CD: Current",
    "0135": "Oxygen Sensor 2 AB: Air-Fuel Equivalence Ratio (lambda,λ) CD: Current",
    "0136": "Oxygen Sensor 3 AB: Air-Fuel Equivalence Ratio (lambda,λ) CD: Current",
    "0137": "Oxygen Sensor 4 AB: Air-Fuel Equivalence Ratio (lambda,λ) CD: Current",
    "0138": "Oxygen Sensor 5 AB: Air-Fuel Equivalence Ratio (lambda,λ) CD: Current",
    "0139": "Oxygen Sensor 6 AB: Air-Fuel Equivalence Ratio (lambda,λ) CD: Current",
    "013a": "Oxygen Sensor 7 AB: Air-Fuel Equivalence Ratio (lambda,λ) CD: Current",
    "013b": "Oxygen Sensor 8 AB: Air-Fuel Equivalence Ratio (lambda,λ) CD: Current",
    "013c": "Catalyst Temperature: Bank 1, Sensor 1",
    "013d": "Catalyst Temperature: Bank 2, Sensor 1",
    "013e": "Catalyst Temperature: Bank 1, Sensor 2",
    "013f": "Catalyst Temperature: Bank 2, Sensor 2",
    "0140": "PIDs supported [$41 - $60]",
    "0141": "Monitor status this drive cycle",
    "0142": "Control module voltage",
    "0143": "Absolute load value",
    "0144": "Commanded Air-Fuel Equivalence Ratio (lambda,λ)",
    "0145": "Relative throttle position",
    "0146": "Ambient air temperature",
    "0147": "Absolute throttle position B",
    "0148": "Absolute throttle position C",
    "0149": "Accelerator pedal position D",
    "014a": "Accelerator pedal position E",
    "014b": "Accelerator pedal position F",
    "014c": "Commanded throttle actuator",
    "014d": "Time run with MIL on",
    "014e": "Time since trouble codes cleared",
    "014f": "Maximum value for Fuel-Air equivalence ratio, oxygen sensor voltage, oxygen sensor current, and intake manifold absolute pressure",
    "0150": "Maximum value for air flow rate from mass air flow sensor",
    "0151": "Fuel Type"
}